{"stats":{"minecraft:killed":{"minecraft:cave_spider":1,"minecraft:cod":9,"minecraft:shulker":18,"minecraft:skeleton":138,"minecraft:guardian":1,"minecraft:chicken":5,"minecraft:tropical_fish":14,"minecraft:magma_cube":22,"minecraft:elder_guardian":2,"minecraft:salmon":4,"minecraft:pillager":40,"minecraft:zombie":1953,"minecraft:cow":83,"minecraft:evoker":5,"minecraft:vindicator":9,"minecraft:horse":4,"minecraft:snow_golem":1,"minecraft:wandering_trader":1,"minecraft:ravager":5,"minecraft:breeze":25,"minecraft:enderman":2259,"minecraft:witch":6,"minecraft:zombified_piglin":1,"minecraft:spider":69,"minecraft:bee":1,"minecraft:silverfish":23,"minecraft:piglin_brute":4,"minecraft:wolf":2,"minecraft:piglin":22,"minecraft:pig":65,"minecraft:zombie_villager":4,"minecraft:creeper":167,"minecraft:sheep":15,"minecraft:trader_llama":1,"minecraft:stray":37,"minecraft:ghast":2,"minecraft:blaze":12,"minecraft:vex":25,"minecraft:slime":40,"minecraft:phantom":6,"minecraft:drowned":12,"minecraft:bat":11,"minecraft:squid":2,"minecraft:wither_skeleton":8},"minecraft:used":{"minecraft:tuff_bricks":75,"minecraft:moss_block":7,"minecraft:dispenser":4,"minecraft:elytra":33,"minecraft:ladder":5,"minecraft:poppy":1,"minecraft:chest":25,"minecraft:stone":80,"minecraft:quartz_stairs":45,"minecraft:rotten_flesh":11,"minecraft:soul_sand":2,"minecraft:deepslate_brick_slab":1715,"minecraft:snowball":27,"minecraft:lava_bucket":7,"minecraft:quartz_pillar":137,"minecraft:wet_sponge":1,"minecraft:diorite_wall":8,"minecraft:bow":740,"minecraft:ominous_bottle":3,"minecraft:oak_sapling":8,"minecraft:furnace":34,"minecraft:egg":8,"minecraft:potato":79,"minecraft:leather_leggings":1,"minecraft:chorus_fruit":2,"minecraft:powered_rail":2,"minecraft:wooden_pickaxe":11,"minecraft:composter":3,"minecraft:oak_leaves":754,"minecraft:golden_apple":4,"minecraft:glow_berries":1,"minecraft:dark_oak_trapdoor":793,"minecraft:sand":12,"minecraft:birch_fence":12,"minecraft:stone_button":2,"minecraft:lectern":151,"minecraft:red_terracotta":1,"minecraft:polished_granite":2,"minecraft:cherry_sign":10,"minecraft:chiseled_tuff_bricks":5,"minecraft:diamond_sword":2986,"minecraft:fire_charge":1,"minecraft:oak_trapdoor":6,"minecraft:oak_boat":1,"minecraft:iron_bars":4,"minecraft:enchanting_table":4,"minecraft:cooked_salmon":2,"minecraft:trial_key":7,"minecraft:netherrack":143,"minecraft:torch":20,"minecraft:brewing_stand":1,"minecraft:anvil":3,"minecraft:iron_axe":354,"minecraft:iron_block":4,"minecraft:cherry_slab":13,"minecraft:totem_of_undying":5,"minecraft:pink_stained_glass_pane":28,"minecraft:diamond_chestplate":20,"minecraft:basalt":6,"minecraft:goat_horn":7,"minecraft:cherry_log":23,"minecraft:cobbled_deepslate":97,"minecraft:orange_terracotta":24,"minecraft:observer":39,"minecraft:wheat_seeds":164,"minecraft:water_bucket":287,"minecraft:lead":1,"minecraft:cartography_table":2,"minecraft:cherry_planks":107,"minecraft:deepslate_bricks":3551,"minecraft:mossy_cobblestone":7,"minecraft:rail":179,"minecraft:tnt":4,"minecraft:crafting_table":16,"minecraft:white_bed":13,"minecraft:campfire":2,"minecraft:oak_log":19,"minecraft:mud":1,"minecraft:ender_eye":3,"minecraft:diamond_pickaxe":22640,"minecraft:ominous_trial_key":4,"minecraft:diamond_shovel":14749,"minecraft:wind_charge":1,"minecraft:oak_button":2,"minecraft:iron_pickaxe":115,"minecraft:cobblestone":1581,"minecraft:potion":5,"minecraft:cooked_porkchop":102,"minecraft:brush":3,"minecraft:stripped_oak_log":9,"minecraft:kelp":5,"minecraft:diamond_leggings":4,"minecraft:cherry_sapling":12,"minecraft:iron_shovel":248,"minecraft:polished_deepslate":84,"minecraft:diamond_hoe":334,"minecraft:decorated_pot":2,"minecraft:shield":70,"minecraft:white_terracotta":238,"minecraft:iron_sword":162,"minecraft:iron_chestplate":8,"minecraft:nether_bricks":49,"minecraft:carrot":318,"minecraft:tuff":17,"minecraft:milk_bucket":5,"minecraft:obsidian":6,"minecraft:glass":96,"minecraft:iron_helmet":2,"minecraft:hay_block":1,"minecraft:scaffolding":138,"minecraft:diamond_boots":1,"minecraft:dark_oak_sign":10,"minecraft:birch_leaves":1,"minecraft:stone_pickaxe":127,"minecraft:ender_pearl":83,"minecraft:sandstone":4,"minecraft:sugar_cane":142,"minecraft:diamond_axe":4212,"minecraft:yellow_terracotta":1,"minecraft:light_gray_terracotta":114,"minecraft:crossbow":3,"minecraft:end_stone":14,"minecraft:lingering_potion":3,"minecraft:shears":839,"minecraft:polished_tuff":5,"minecraft:redstone_torch":2,"minecraft:lever":6,"minecraft:firework_rocket":206,"minecraft:birch_fence_gate":1,"minecraft:dark_oak_log":2,"minecraft:melon_slice":46,"minecraft:bread":210,"minecraft:golden_helmet":3,"minecraft:grindstone":3,"minecraft:andesite":6,"minecraft:waxed_copper_bulb":6,"minecraft:bone_meal":66,"minecraft:oak_fence":100,"minecraft:cherry_boat":1,"minecraft:experience_bottle":2,"minecraft:netherite_sword":346,"minecraft:trident":1,"minecraft:tropical_fish":14,"minecraft:flint_and_steel":56,"minecraft:stone_shovel":123,"minecraft:redstone":33,"minecraft:ender_chest":22,"minecraft:wooden_shovel":6,"minecraft:spyglass":512,"minecraft:dirt":1524,"minecraft:white_carpet":94,"minecraft:hopper":27,"minecraft:diamond_helmet":14,"minecraft:shulker_box":36,"minecraft:golden_chestplate":1,"minecraft:granite":48,"minecraft:birch_door":5,"minecraft:bookshelf":67,"minecraft:cherry_trapdoor":7,"minecraft:red_candle":1,"minecraft:iron_boots":5,"minecraft:netherite_pickaxe":1853,"minecraft:minecart":8,"minecraft:cooked_beef":154,"minecraft:pumpkin":1,"minecraft:iron_leggings":6,"minecraft:cooked_mutton":5,"minecraft:acacia_boat":1,"minecraft:glass_bottle":13,"minecraft:netherite_chestplate":15,"minecraft:baked_potato":23,"minecraft:cobblestone_slab":24,"minecraft:waxed_copper_block":10,"minecraft:terracotta":1,"minecraft:book":1,"minecraft:piston":34,"minecraft:stone_axe":74,"minecraft:pink_petals":10,"minecraft:white_banner":1,"minecraft:bucket":300,"minecraft:yellow_bed":2,"minecraft:splash_potion":1},"minecraft:custom":{"minecraft:interact_with_crafting_table":237,"minecraft:open_barrel":22,"minecraft:bell_ring":137,"minecraft:leave_game":30,"minecraft:time_since_death":211699,"minecraft:damage_blocked_by_shield":3930,"minecraft:play_time":3281844,"minecraft:deaths":126,"minecraft:jump":33931,"minecraft:enchant_item":159,"minecraft:interact_with_furnace":389,"minecraft:play_record":2,"minecraft:traded_with_villager":120,"minecraft:sleep_in_bed":46,"minecraft:damage_dealt":258513,"minecraft:interact_with_smithing_table":11,"minecraft:interact_with_smoker":14,"minecraft:inspect_dispenser":23,"minecraft:use_cauldron":3,"minecraft:horse_one_cm":146000,"minecraft:interact_with_anvil":34,"minecraft:inspect_hopper":24,"minecraft:sneak_time":249437,"minecraft:interact_with_blast_furnace":30,"minecraft:total_world_time":3281844,"minecraft:interact_with_stonecutter":10,"minecraft:time_since_rest":211725,"minecraft:swim_one_cm":485662,"minecraft:fly_one_cm":5685666,"minecraft:open_chest":2605,"minecraft:fall_one_cm":908290,"minecraft:animals_bred":39,"minecraft:open_shulker_box":193,"minecraft:sprint_one_cm":5405592,"minecraft:drop":1241,"minecraft:talked_to_villager":222,"minecraft:interact_with_brewingstand":12,"minecraft:walk_on_water_one_cm":379358,"minecraft:interact_with_loom":2,"minecraft:open_enderchest":58,"minecraft:player_kills":6,"minecraft:crouch_one_cm":1057041,"minecraft:mob_kills":5193,"minecraft:climb_one_cm":72091,"minecraft:walk_one_cm":6587855,"minecraft:raid_win":1,"minecraft:walk_under_water_one_cm":414410,"minecraft:boat_one_cm":397006,"minecraft:raid_trigger":1,"minecraft:interact_with_grindstone":110,"minecraft:damage_taken":62269,"minecraft:damage_absorbed":349,"minecraft:aviate_one_cm":6444268},"minecraft:picked_up":{"minecraft:birch_door":6,"minecraft:iron_chestplate":19,"minecraft:chainmail_boots":3,"minecraft:suspicious_stew":6,"minecraft:flower_pot":2,"minecraft:anvil":1,"minecraft:prismarine_shard":3,"minecraft:lead":1,"minecraft:diamond_sword":17,"minecraft:oak_stairs":142,"minecraft:enchanted_book":2,"minecraft:brewing_stand":4,"minecraft:golden_sword":1,"minecraft:polished_deepslate":11,"minecraft:string":229,"minecraft:dark_oak_trapdoor":337,"minecraft:soul_soil":34,"minecraft:cooked_salmon":3,"minecraft:explorer_pottery_sherd":4,"minecraft:cherry_boat":3,"minecraft:diamond_leggings":20,"minecraft:gold_nugget":248,"minecraft:cobbled_deepslate":4614,"minecraft:trial_key":8,"minecraft:netherite_upgrade_smithing_template":8,"minecraft:melon_slice":174,"minecraft:golden_helmet":12,"minecraft:composter":1,"minecraft:acacia_log":1,"minecraft:cherry_log":92,"minecraft:waxed_weathered_copper_bulb":6,"minecraft:waxed_copper_grate":10,"minecraft:golden_chestplate":6,"minecraft:orange_bed":1,"minecraft:stone_sword":1,"minecraft:honey_bottle":6,"minecraft:tropical_fish":14,"minecraft:armadillo_scute":1,"minecraft:iron_block":1,"minecraft:glowstone":3,"minecraft:bookshelf":746,"minecraft:white_terracotta":375,"minecraft:netherite_chestplate":2,"minecraft:blaze_rod":32,"minecraft:iron_bars":26,"minecraft:snowball":59,"minecraft:birch_log":31,"minecraft:furnace_minecart":1,"minecraft:magma_block":4,"minecraft:feather":9,"minecraft:cooked_beef":351,"minecraft:iron_door":19,"minecraft:water_bucket":8,"minecraft:jungle_log":7,"minecraft:brown_wool":1,"minecraft:flint":69,"minecraft:cherry_fence":3,"minecraft:map":3,"minecraft:lantern":1,"minecraft:dark_oak_sign":4,"minecraft:diamond_helmet":31,"minecraft:glowstone_dust":74,"minecraft:moss_block":10,"minecraft:birch_fence_gate":1,"minecraft:ink_sac":8,"minecraft:dark_oak_log":1561,"minecraft:red_terracotta":3,"minecraft:dispenser":3,"minecraft:deepslate":123,"minecraft:lever":6,"minecraft:granite":507,"minecraft:bread":274,"minecraft:music_disc_precipice":2,"minecraft:rooted_dirt":38,"minecraft:plenty_pottery_sherd":5,"minecraft:cherry_slab":4,"minecraft:ominous_trial_key":5,"minecraft:crimson_roots":5,"minecraft:diamond_pickaxe":36,"minecraft:crafting_table":13,"minecraft:mud":1,"minecraft:ominous_bottle":8,"minecraft:nether_wart":40,"minecraft:clay_ball":818,"minecraft:golden_pickaxe":1,"minecraft:leather_leggings":6,"minecraft:mourner_pottery_sherd":2,"minecraft:music_disc_creator":1,"minecraft:purpur_block":4,"minecraft:wind_charge":5,"minecraft:cornflower":1,"minecraft:elytra":2,"minecraft:flow_banner_pattern":2,"minecraft:flint_and_steel":3,"minecraft:netherite_scrap":3,"minecraft:white_stained_glass":4,"minecraft:white_carpet":6,"minecraft:iron_shovel":1,"minecraft:glass_pane":76,"minecraft:cracked_stone_bricks":3,"minecraft:cartography_table":2,"minecraft:netherite_sword":1,"minecraft:beef":199,"minecraft:chiseled_tuff":2,"minecraft:jungle_sapling":3,"minecraft:iron_nugget":18,"minecraft:poppy":16,"minecraft:minecart":7,"minecraft:quartz_stairs":3,"minecraft:chest":33,"minecraft:piston":2,"minecraft:waxed_oxidized_copper":43,"minecraft:egg":16,"minecraft:black_stained_glass":4,"minecraft:sandstone":8,"minecraft:stone":355,"minecraft:oak_door":2,"minecraft:carrot":1442,"minecraft:redstone":418,"minecraft:prismarine_crystals":8,"minecraft:tnt":17,"minecraft:stone_shovel":4,"minecraft:diamond_chestplate":22,"minecraft:cooked_cod":6,"minecraft:decorated_pot":32,"minecraft:peony":1,"minecraft:deepslate_bricks":1268,"minecraft:shears":3,"minecraft:diamond_boots":6,"minecraft:hay_block":179,"minecraft:yellow_terracotta":16,"minecraft:flow_armor_trim_smithing_template":3,"minecraft:gold_ingot":9,"minecraft:totem_of_undying":7,"minecraft:tuff_bricks":478,"minecraft:glow_berries":3,"minecraft:mutton":33,"minecraft:white_wool":201,"minecraft:rail":126,"minecraft:oxeye_daisy":2,"minecraft:stripped_oak_log":41,"minecraft:birch_leaves":5,"minecraft:clock":1,"minecraft:red_glazed_terracotta":2,"minecraft:red_mushroom":4,"minecraft:filled_map":10,"minecraft:oak_log":1058,"minecraft:lily_pad":20,"minecraft:ancient_debris":23,"minecraft:golden_boots":7,"minecraft:paper":334,"minecraft:white_banner":15,"minecraft:stone_bricks":5,"minecraft:apple":24,"minecraft:kelp":80,"minecraft:stone_pickaxe":8,"minecraft:blade_pottery_sherd":1,"minecraft:cherry_sign":6,"minecraft:glass_bottle":22,"minecraft:iron_sword":17,"minecraft:flowering_azalea":24,"minecraft:light_gray_stained_glass":17,"minecraft:waxed_exposed_copper_bulb":4,"minecraft:spyglass":36,"minecraft:gravel":755,"minecraft:polished_tuff":70,"minecraft:sea_lantern":8,"minecraft:dragon_egg":1,"minecraft:leather_helmet":4,"minecraft:firework_rocket":22,"minecraft:diamond_shovel":7,"minecraft:slime_ball":126,"minecraft:stone_axe":2,"minecraft:rib_armor_trim_smithing_template":4,"minecraft:short_grass":1,"minecraft:diamond_axe":16,"minecraft:baked_potato":19,"minecraft:melon_seeds":3,"minecraft:mangrove_propagule":2,"minecraft:hopper":11,"minecraft:ender_pearl":1735,"minecraft:shulker_shell":12,"minecraft:wheat":183,"minecraft:ender_chest":20,"minecraft:light_gray_shulker_box":1,"minecraft:potion":7,"minecraft:nether_brick":9,"minecraft:crimson_planks":180,"minecraft:raw_copper":123,"minecraft:iron_leggings":14,"minecraft:red_candle":24,"minecraft:experience_bottle":4,"minecraft:pink_shulker_box":1,"minecraft:bucket":11,"minecraft:redstone_torch":1,"minecraft:cobblestone_slab":24,"minecraft:ender_eye":5,"minecraft:calcite":4,"minecraft:azalea":22,"minecraft:iron_pickaxe":2,"minecraft:iron_boots":15,"minecraft:furnace":32,"minecraft:tipped_arrow":57,"minecraft:stick":334,"minecraft:oak_fence":43,"minecraft:torch":101,"minecraft:porkchop":177,"minecraft:pointed_dripstone":10,"minecraft:diorite":346,"minecraft:rotten_flesh":1861,"minecraft:obsidian":32,"minecraft:cod":28,"minecraft:blaze_powder":2,"minecraft:cobblestone":7083,"minecraft:enchanting_table":1,"minecraft:pink_petals":1088,"minecraft:leather_chestplate":1,"minecraft:magma_cream":13,"minecraft:cherry_planks":65,"minecraft:andesite":120,"minecraft:golden_leggings":12,"minecraft:potato":304,"minecraft:tuff":229,"minecraft:prismarine_bricks":6,"minecraft:acacia_boat":3,"minecraft:lapis_lazuli":929,"minecraft:dirt":7240,"minecraft:polished_granite":2,"minecraft:name_tag":1,"minecraft:leather_boots":3,"minecraft:glass":5,"minecraft:bone":523,"minecraft:bow":51,"minecraft:wheat_seeds":562,"minecraft:cobbled_deepslate_wall":2,"minecraft:deepslate_brick_slab":407,"minecraft:raw_gold":20,"minecraft:bell":1,"minecraft:grindstone":2,"minecraft:bolt_armor_trim_smithing_template":1,"minecraft:mossy_stone_bricks":4,"minecraft:bamboo":1041,"minecraft:powered_rail":6,"minecraft:prismarine":5,"minecraft:oak_planks":593,"minecraft:ghast_tear":3,"minecraft:diorite_wall":60,"minecraft:cooked_porkchop":189,"minecraft:waxed_oxidized_copper_bulb":3,"minecraft:poisonous_potato":23,"minecraft:sand":1022,"minecraft:grass_block":1,"minecraft:shulker_box":46,"minecraft:spectral_arrow":36,"minecraft:mossy_cobblestone":114,"minecraft:dark_prismarine":3,"minecraft:light_gray_terracotta":309,"minecraft:sugar":2,"minecraft:clay":192,"minecraft:diamond":393,"minecraft:waxed_oxidized_copper_grate":13,"minecraft:crossbow":3,"minecraft:breeze_rod":140,"minecraft:golden_apple":7,"minecraft:emerald":153,"minecraft:oak_sapling":118,"minecraft:netherrack":2719,"minecraft:chorus_fruit":2,"minecraft:oak_leaves":766,"minecraft:cocoa_beans":19,"minecraft:end_stone_bricks":8,"minecraft:fishing_rod":7,"minecraft:charcoal":2,"minecraft:splash_potion":1,"minecraft:chicken":12,"minecraft:wooden_pickaxe":9,"minecraft:gold_block":3,"minecraft:chain":1,"minecraft:brick":13,"minecraft:shield":11,"minecraft:oak_trapdoor":28,"minecraft:moss_carpet":8,"minecraft:iron_axe":17,"minecraft:birch_fence":4,"minecraft:blackstone":66,"minecraft:oak_boat":2,"minecraft:observer":7,"minecraft:light_gray_wool":7,"minecraft:lectern":145,"minecraft:sugar_cane":899,"minecraft:cherry_trapdoor":2,"minecraft:phantom_membrane":2,"minecraft:dark_oak_sapling":27,"minecraft:raw_iron":578,"minecraft:end_stone":54,"minecraft:copper_ingot":1,"minecraft:polished_blackstone_bricks":5,"minecraft:quartz_pillar":15,"minecraft:stone_button":1,"minecraft:music_disc_11":2,"minecraft:trident":1,"minecraft:cherry_fence_gate":1,"minecraft:arrow":1359,"minecraft:golden_hoe":1,"minecraft:nether_bricks":107,"minecraft:saddle":41,"minecraft:wet_sponge":3,"minecraft:basalt":17,"minecraft:golden_carrot":4,"minecraft:glow_ink_sac":2,"minecraft:crimson_stem":15,"minecraft:salmon":2,"minecraft:leather":338,"minecraft:waxed_copper_bulb":26,"minecraft:waxed_copper_block":177,"minecraft:yellow_bed":1,"minecraft:gunpowder":356,"minecraft:cobblestone_stairs":1,"minecraft:wooden_hoe":1,"minecraft:orange_terracotta":31,"minecraft:cooked_mutton":6,"minecraft:coast_armor_trim_smithing_template":2,"minecraft:heart_of_the_sea":2,"minecraft:iron_ingot":262,"minecraft:polished_tuff_slab":1,"minecraft:cooked_chicken":1,"minecraft:stripped_oak_wood":5,"minecraft:soul_sand":46,"minecraft:book":58,"minecraft:scaffolding":14,"minecraft:nether_quartz_ore":2,"minecraft:pumpkin":4,"minecraft:chiseled_stone_bricks":1,"minecraft:brush":3,"minecraft:quartz":881,"minecraft:dandelion":3,"minecraft:dripstone_block":4,"minecraft:lava_bucket":11,"minecraft:amethyst_shard":22,"minecraft:white_bed":9,"minecraft:spider_eye":133,"minecraft:pumpkin_seeds":11,"minecraft:chainmail_leggings":2,"minecraft:iron_helmet":4,"minecraft:cherry_sapling":27,"minecraft:terracotta":21,"minecraft:red_concrete":2,"minecraft:coal":936,"minecraft:chiseled_tuff_bricks":45},"minecraft:dropped":{"minecraft:clay":126,"minecraft:iron_sword":5,"minecraft:short_grass":1,"minecraft:ominous_bottle":5,"minecraft:lapis_lazuli":186,"minecraft:cooked_beef":68,"minecraft:diamond":77,"minecraft:cooked_porkchop":23,"minecraft:rooted_dirt":38,"minecraft:cracked_stone_bricks":1,"minecraft:saddle":2,"minecraft:quartz_pillar":2,"minecraft:elytra":1,"minecraft:leather_helmet":5,"minecraft:emerald":1,"minecraft:dirt":460,"minecraft:dark_oak_trapdoor":147,"minecraft:chain":1,"minecraft:bone_meal":192,"minecraft:white_wool":6,"minecraft:bone":174,"minecraft:stone_axe":12,"minecraft:cherry_boat":1,"minecraft:sugar_cane":3,"minecraft:ancient_debris":3,"minecraft:golden_chestplate":6,"minecraft:cobbled_deepslate":316,"minecraft:nether_brick":9,"minecraft:wheat":74,"minecraft:rotten_flesh":191,"minecraft:oak_planks":4,"minecraft:white_bed":14,"minecraft:waxed_copper_block":3,"minecraft:red_candle":13,"minecraft:diorite_wall":3,"minecraft:jungle_log":1,"minecraft:leather_boots":1,"minecraft:leather_leggings":5,"minecraft:end_stone_bricks":2,"minecraft:glass":2,"minecraft:beef":2,"minecraft:cherry_fence":3,"minecraft:egg":1,"minecraft:enchanted_book":9,"minecraft:golden_boots":8,"minecraft:birch_leaves":4,"minecraft:wheat_seeds":236,"minecraft:netherite_chestplate":1,"minecraft:cobbled_deepslate_wall":2,"minecraft:iron_helmet":1,"minecraft:feather":2,"minecraft:cobblestone":355,"minecraft:granite":74,"minecraft:chainmail_helmet":2,"minecraft:coal":1,"minecraft:golden_apple":2,"minecraft:diamond_helmet":6,"minecraft:potion":6,"minecraft:armadillo_scute":1,"minecraft:iron_shovel":1,"minecraft:paper":311,"minecraft:string":6,"minecraft:furnace":2,"minecraft:moss_carpet":4,"minecraft:soul_soil":13,"minecraft:netherite_ingot":2,"minecraft:stone_sword":1,"minecraft:cocoa_beans":9,"minecraft:deepslate":120,"minecraft:chicken":3,"minecraft:clay_ball":22,"minecraft:iron_boots":5,"minecraft:cherry_slab":1,"minecraft:shears":2,"minecraft:diamond_sword":10,"minecraft:potato":189,"minecraft:hay_block":28,"minecraft:stone":6,"minecraft:flower_pot":1,"minecraft:diamond_pickaxe":5,"minecraft:pink_shulker_box":1,"minecraft:bamboo":62,"minecraft:spider_eye":13,"minecraft:bow":3,"minecraft:magma_block":4,"minecraft:terracotta":20,"minecraft:soul_sand":13,"minecraft:diamond_axe":5,"minecraft:oak_log":42,"minecraft:ender_pearl":3458,"minecraft:decorated_pot":22,"minecraft:netherite_upgrade_smithing_template":16,"minecraft:lantern":1,"minecraft:leather":97,"minecraft:honeycomb":13,"minecraft:cod":2,"minecraft:brush":3,"minecraft:cherry_trapdoor":1,"minecraft:mutton":1,"minecraft:music_disc_precipice":1,"minecraft:snowball":1,"minecraft:gold_ingot":3,"minecraft:gravel":75,"minecraft:blackstone":66,"minecraft:spyglass":2,"minecraft:chiseled_tuff_bricks":1,"minecraft:diamond_shovel":3,"minecraft:carrot":664,"minecraft:chainmail_chestplate":1,"minecraft:shulker_shell":13,"minecraft:leather_chestplate":1,"minecraft:trident":1,"minecraft:azalea":11,"minecraft:chainmail_boots":2,"minecraft:basalt":10,"minecraft:arrow":212,"minecraft:powered_rail":6,"minecraft:oak_leaves":3,"minecraft:splash_potion":1,"minecraft:netherrack":1281,"minecraft:firework_rocket":53,"minecraft:water_bucket":6,"minecraft:bread":52,"minecraft:golden_helmet":6,"minecraft:cherry_log":17,"minecraft:sniffer_egg":1,"minecraft:diamond_leggings":5,"minecraft:poisonous_potato":2,"minecraft:plenty_pottery_sherd":1,"minecraft:polished_tuff":59,"minecraft:amethyst_block":7,"minecraft:ominous_trial_key":1,"minecraft:stick":26,"minecraft:cherry_fence_gate":1,"minecraft:iron_block":2,"minecraft:milk_bucket":4,"minecraft:diorite":73,"minecraft:torch":42,"minecraft:light_gray_shulker_box":1,"minecraft:waxed_copper_bulb":9,"minecraft:map":1,"minecraft:waxed_oxidized_copper":1,"minecraft:iron_leggings":3,"minecraft:flowering_azalea":12,"minecraft:pink_petals":3,"minecraft:bucket":2,"minecraft:redstone":36,"minecraft:kelp":11,"minecraft:tuff_bricks":3,"minecraft:oak_trapdoor":16,"minecraft:ender_chest":1,"minecraft:blaze_rod":3,"minecraft:raw_copper":4,"minecraft:light_gray_terracotta":125,"minecraft:tuff":58,"minecraft:light_gray_wool":1,"minecraft:shulker_box":4,"minecraft:glass_pane":144,"minecraft:red_terracotta":2,"minecraft:deepslate_bricks":648,"minecraft:filled_map":2,"minecraft:shield":2,"minecraft:trial_key":1,"minecraft:diamond_chestplate":5,"minecraft:iron_chestplate":2,"minecraft:andesite":4,"minecraft:mossy_stone_bricks":1,"minecraft:golden_leggings":2,"minecraft:oak_sapling":8,"minecraft:diamond_boots":3,"minecraft:slime_ball":63,"minecraft:stone_pickaxe":14,"minecraft:wooden_pickaxe":2,"minecraft:nether_quartz_ore":2,"minecraft:waxed_oxidized_copper_grate":2},"minecraft:killed_by":{"minecraft:piglin_brute":3,"minecraft:ravager":1,"minecraft:vindicator":2,"minecraft:zombie":5,"minecraft:vex":13,"minecraft:guardian":2,"minecraft:evoker":2,"minecraft:wither_skeleton":3,"minecraft:creeper":3,"minecraft:drowned":3,"minecraft:piglin":3,"minecraft:player":26,"minecraft:spider":1,"minecraft:enderman":6,"minecraft:hoglin":1,"minecraft:skeleton":12},"minecraft:broken":{"minecraft:diamond_helmet":1,"minecraft:shears":3,"minecraft:iron_sword":1,"minecraft:diamond_leggings":1,"minecraft:iron_axe":1,"minecraft:stone_pickaxe":1,"minecraft:diamond_boots":1,"minecraft:stone_axe":1},"minecraft:mined":{"minecraft:dragon_wall_head":1,"minecraft:white_bed":8,"minecraft:cherry_log":75,"minecraft:jungle_leaves":24,"minecraft:obsidian":26,"minecraft:potted_dead_bush":1,"minecraft:granite":443,"minecraft:acacia_log":2,"minecraft:jungle_log":6,"minecraft:deepslate_bricks":1092,"minecraft:chiseled_tuff_bricks":52,"minecraft:hopper":11,"minecraft:oxeye_daisy":1,"minecraft:nether_wart":10,"minecraft:chiseled_stone_bricks":1,"minecraft:spawner":2,"minecraft:polished_blackstone_bricks":11,"minecraft:weeping_vines_plant":1,"minecraft:magma_block":35,"minecraft:dark_oak_trapdoor":285,"minecraft:cobbled_deepslate":28,"minecraft:barrel":1,"minecraft:fire":30,"minecraft:waxed_oxidized_copper_bulb":3,"minecraft:deepslate_lapis_ore":37,"minecraft:nether_brick_stairs":1,"minecraft:enchanting_table":1,"minecraft:cave_vines":1,"minecraft:dirt_path":311,"minecraft:oak_stairs":142,"minecraft:kelp_plant":3,"minecraft:amethyst_cluster":3,"minecraft:torch":22,"minecraft:melon":1,"minecraft:glass":7,"minecraft:sugar_cane":397,"minecraft:cherry_slab":2,"minecraft:white_terracotta":382,"minecraft:cherry_fence":5,"minecraft:waxed_copper_bulb":26,"minecraft:light_gray_stained_glass":18,"minecraft:wheat":85,"minecraft:waxed_copper_block":202,"minecraft:birch_door":5,"minecraft:smooth_basalt":1,"minecraft:piston":2,"minecraft:deepslate":4718,"minecraft:infested_deepslate":3,"minecraft:yellow_terracotta":16,"minecraft:deepslate_tiles":1,"minecraft:dark_prismarine":3,"minecraft:mossy_cobblestone":120,"minecraft:cherry_sapling":1,"minecraft:dark_oak_log":1574,"minecraft:end_stone":58,"minecraft:sea_lantern":8,"minecraft:shulker_box":42,"minecraft:waxed_oxidized_chiseled_copper":1,"minecraft:nether_bricks":58,"minecraft:birch_fence_gate":1,"minecraft:crimson_roots":1,"minecraft:redstone_wire":1,"minecraft:kelp":8,"minecraft:red_mushroom":4,"minecraft:cartography_table":2,"minecraft:moss_block":3,"minecraft:cherry_wall_sign":4,"minecraft:waxed_oxidized_cut_copper":12,"minecraft:waxed_copper_grate":15,"minecraft:snow":90,"minecraft:andesite":121,"minecraft:chiseled_tuff":2,"minecraft:potatoes":73,"minecraft:vine":5,"minecraft:cobblestone_slab":24,"minecraft:rail":56,"minecraft:bamboo":85,"minecraft:waxed_weathered_copper_bulb":7,"minecraft:cherry_fence_gate":1,"minecraft:ender_chest":21,"minecraft:oak_slab":1,"minecraft:glass_pane":12,"minecraft:cherry_planks":66,"minecraft:soul_sand":58,"minecraft:observer":7,"minecraft:dandelion":6,"minecraft:cornflower":1,"minecraft:cobbled_deepslate_wall":2,"minecraft:short_grass":416,"minecraft:campfire":1,"minecraft:copper_ore":23,"minecraft:tall_grass":65,"minecraft:deepslate_gold_ore":8,"minecraft:diorite":343,"minecraft:black_stained_glass":4,"minecraft:red_terracotta":2,"minecraft:dark_oak_wall_sign":3,"minecraft:white_carpet":4,"minecraft:birch_leaves":8,"minecraft:quartz_pillar":15,"minecraft:dark_oak_sign":1,"minecraft:pink_stained_glass_pane":1,"minecraft:gravel":791,"minecraft:cobweb":2,"minecraft:stone_bricks":5,"minecraft:waxed_cut_copper_slab":5,"minecraft:large_amethyst_bud":3,"minecraft:oak_sapling":1,"minecraft:farmland":10,"minecraft:sculk_vein":2,"minecraft:cobblestone_stairs":4,"minecraft:brewing_stand":2,"minecraft:cherry_trapdoor":1,"minecraft:cave_vines_plant":3,"minecraft:grass_block":6996,"minecraft:cracked_polished_blackstone_bricks":2,"minecraft:soul_soil":69,"minecraft:composter":1,"minecraft:tuff_bricks":718,"minecraft:glowstone":15,"minecraft:iron_ore":119,"minecraft:polished_tuff":36,"minecraft:anvil":1,"minecraft:azure_bluet":1,"minecraft:polished_tuff_slab":5,"minecraft:azalea_leaves":3,"minecraft:end_stone_bricks":6,"minecraft:waxed_cut_copper":3,"minecraft:deepslate_redstone_ore":51,"minecraft:blackstone":108,"minecraft:orange_terracotta":31,"minecraft:clay":196,"minecraft:light_gray_terracotta":308,"minecraft:chest":27,"minecraft:nether_quartz_ore":293,"minecraft:cobblestone":1404,"minecraft:prismarine":6,"minecraft:waxed_chiseled_copper":1,"minecraft:grindstone":2,"minecraft:oak_planks":233,"minecraft:iron_door":16,"minecraft:wall_torch":8,"minecraft:deepslate_copper_ore":6,"minecraft:pink_petals":199,"minecraft:seagrass":1,"minecraft:red_candle":1,"minecraft:birch_log":26,"minecraft:waxed_oxidized_cut_copper_stairs":1,"minecraft:stripped_oak_wood":5,"minecraft:purpur_block":4,"minecraft:oak_log":953,"minecraft:diorite_wall":1,"minecraft:waxed_oxidized_copper":53,"minecraft:sand":1270,"minecraft:dirt":5348,"minecraft:dispenser":3,"minecraft:netherrack":4396,"minecraft:ancient_debris":14,"minecraft:oak_leaves":1074,"minecraft:nether_gold_ore":40,"minecraft:tuff":278,"minecraft:quartz_stairs":3,"minecraft:dark_oak_leaves":16,"minecraft:deepslate_diamond_ore":165,"minecraft:oak_door":2,"minecraft:glow_lichen":2,"minecraft:lever":6,"minecraft:decorated_pot":40,"minecraft:weeping_vines":2,"minecraft:white_stained_glass":4,"minecraft:rooted_dirt":2,"minecraft:sandstone":8,"minecraft:crimson_stem":15,"minecraft:hay_block":167,"minecraft:deepslate_brick_slab":257,"minecraft:oak_trapdoor":12,"minecraft:furnace":18,"minecraft:carrots":232,"minecraft:gold_block":3,"minecraft:bell":1,"minecraft:polished_deepslate":11,"minecraft:bookshelf":502,"minecraft:deepslate_iron_ore":126,"minecraft:lantern":1,"minecraft:stripped_oak_log":41,"minecraft:packed_ice":3,"minecraft:wet_sponge":1,"minecraft:stone":7295,"minecraft:waxed_exposed_copper_bulb":5,"minecraft:scaffolding":11,"minecraft:acacia_leaves":6,"minecraft:basalt":39,"minecraft:polished_granite":2,"minecraft:oak_fence":43,"minecraft:crafting_table":13,"minecraft:lectern":146,"minecraft:red_glazed_terracotta":4,"minecraft:lapis_ore":3,"minecraft:sculk":198,"minecraft:prismarine_bricks":6,"minecraft:waxed_oxidized_copper_grate":15,"minecraft:redstone_torch":1,"minecraft:ice":102,"minecraft:yellow_bed":1,"minecraft:coal_ore":253,"minecraft:cocoa":1,"minecraft:cherry_leaves":7,"minecraft:flower_pot":1,"minecraft:cracked_stone_bricks":4,"minecraft:terracotta":21,"minecraft:mossy_stone_bricks":5,"minecraft:birch_fence":4},"minecraft:crafted":{"minecraft:ender_chest":3,"minecraft:blaze_powder":14,"minecraft:lever":1,"minecraft:diamond_shovel":5,"minecraft:bookshelf":27,"minecraft:cooked_mutton":2,"minecraft:iron_bars":16,"minecraft:quartz_block":167,"minecraft:glass":455,"minecraft:diamond_helmet":7,"minecraft:diamond_leggings":5,"minecraft:birch_fence_gate":1,"minecraft:glass_bottle":12,"minecraft:wooden_shovel":1,"minecraft:emerald":65,"minecraft:cooked_porkchop":121,"minecraft:diamond_axe":3,"minecraft:copper_ingot":13,"minecraft:campfire":2,"minecraft:lectern":13,"minecraft:cherry_sign":9,"minecraft:iron_pickaxe":1,"minecraft:iron_block":10,"minecraft:gold_ingot":123,"minecraft:netherite_ingot":5,"minecraft:composter":2,"minecraft:spyglass":4,"minecraft:diamond_hoe":1,"minecraft:bone_meal":225,"minecraft:pink_dye":12,"minecraft:white_carpet":90,"minecraft:cherry_trapdoor":6,"minecraft:lantern":12,"minecraft:diamond":9,"minecraft:polished_diorite":192,"minecraft:stone_pickaxe":14,"minecraft:diamond_boots":5,"minecraft:dark_oak_planks":1820,"minecraft:wheat":270,"minecraft:crossbow":4,"minecraft:enchanting_table":3,"minecraft:deepslate_brick_slab":1380,"minecraft:polished_granite":4,"minecraft:enchanted_book":16,"minecraft:iron_shovel":1,"minecraft:iron_leggings":3,"minecraft:white_bed":20,"minecraft:oak_planks":672,"minecraft:cobblestone_slab":24,"minecraft:stone":6,"minecraft:quartz_pillar":13,"minecraft:hopper":16,"minecraft:bow":8,"minecraft:iron_boots":3,"minecraft:chest":45,"minecraft:oak_button":2,"minecraft:netherite_upgrade_smithing_template":30,"minecraft:rail":80,"minecraft:ender_eye":11,"minecraft:oak_fence":78,"minecraft:quartz_stairs":1,"minecraft:arrow":8,"minecraft:crafting_table":7,"minecraft:wooden_pickaxe":2,"minecraft:iron_helmet":1,"minecraft:gold_block":13,"minecraft:birch_planks":56,"minecraft:dispenser":3,"minecraft:book":75,"minecraft:iron_chestplate":3,"minecraft:paper":1236,"minecraft:diamond_pickaxe":6,"minecraft:shield":2,"minecraft:birch_fence":9,"minecraft:stick":180,"minecraft:iron_ingot":422,"minecraft:snow_block":8,"minecraft:redstone_torch":1,"minecraft:dark_oak_fence_gate":1,"minecraft:deepslate_bricks":3968,"minecraft:shears":5,"minecraft:cherry_planks":184,"minecraft:raw_iron":9,"minecraft:furnace":16,"minecraft:stone_button":1,"minecraft:piston":32,"minecraft:dark_oak_trapdoor":598,"minecraft:dark_oak_sign":6,"minecraft:glass_pane":768,"minecraft:oak_trapdoor":8,"minecraft:flint_and_steel":1,"minecraft:scaffolding":396,"minecraft:polished_deepslate":4048,"minecraft:iron_axe":2,"minecraft:netherite_scrap":20,"minecraft:observer":32,"minecraft:minecart":2,"minecraft:cooked_beef":161,"minecraft:crimson_planks":60,"minecraft:diamond_sword":8,"minecraft:powered_rail":6,"minecraft:iron_sword":1,"minecraft:bucket":5,"minecraft:stone_axe":12,"minecraft:air":0,"minecraft:bread":39,"minecraft:oak_boat":1,"minecraft:pink_stained_glass_pane":96,"minecraft:anvil":2,"minecraft:acacia_planks":4,"minecraft:torch":40,"minecraft:clay":190,"minecraft:diamond_chestplate":5,"minecraft:firework_rocket":258}},"DataVersion":3953}